nonebot_plugin_bilibilibot/__init__.py
nonebot_plugin_bilibilibot/config.py
nonebot_plugin_bilibilibot/bili_src/basicFunc.py
nonebot_plugin_bilibilibot/bili_src/biliStream.py
nonebot_plugin_bilibilibot/bili_src/biliTelegram.py
nonebot_plugin_bilibilibot/bili_src/biliVideo.py
nonebot_plugin_bilibilibot/bili_src/bili_client.py
nonebot_plugin_bilibilibot/bili_src/bili_dynamic.py
nonebot_plugin_bilibilibot/bili_src/bili_dynamic_dbg.py
nonebot_plugin_bilibilibot/bili_src/bili_task.py
nonebot_plugin_bilibilibot/bili_src/db.py
nonebot_plugin_bilibilibot/bili_src/exception.py
nonebot_plugin_bilibilibot/bili_src/rule.py
nonebot_plugin_bilibilibot/file/source/announcement.json
nonebot_plugin_bilibilibot/file/source/help.json
nonebot_plugin_bilibilibot-2.3.4.dist-info/LICENSE
nonebot_plugin_bilibilibot-2.3.4.dist-info/METADATA
nonebot_plugin_bilibilibot-2.3.4.dist-info/WHEEL
nonebot_plugin_bilibilibot-2.3.4.dist-info/top_level.txt
nonebot_plugin_bilibilibot-2.3.4.dist-info/RECORD
