Metadata-Version: 2.1
Name: nonebot-plugin-bilibilibot
Version: 2.3.4
Summary: 基于Nonebot的bilibili通知插件，可将up主，主播以及番剧的更新/直播动态推送到QQ
Home-page: https://github.com/TDK1969/nonebot_plugin_bilibilibot
Author: TDK
Author-email: tdk1969@foxmail.com
License: GNU
Keywords: nonebot
Platform: UNKNOWN
Classifier: Programming Language :: Python :: 3
Classifier: License :: OSI Approved :: GNU General Public License v3 (GPLv3)
Classifier: Operating System :: OS Independent
License-File: LICENSE
Requires-Dist: httpx
Requires-Dist: nonebot-plugin-apscheduler
Requires-Dist: nonebot-adapter-onebot
